Metadata-Version: 1.1
Name: coarse
Version: 0.0.1
Summary: your_name_here
Home-page: https://github.com/cmutel/coarse
Author: Chris Mutel
Author-email: cmutel@gmail.com
License: BSD 3-Clause License
